{
  "_id": "dark-legacy",
  "name": "Dark (legacy)",
  "themeSource": "dark",
  "variables": {
    "--text-color": "#E1E1E6",
    "--view-bg": "#191622",
    "--border-color": "#1F1F1F",
    "--border-radius": "2px",

    "--header-color": "#E1E1E6",
    "--header-bg": "#201B2D",

    "--footer-bg": "#201B2D",
    "--footer-nav-bg-color-active": "#191622",

    "--tracks-bg-even": "#191622",
    "--tracks-bg-odd": "#15121E",

    "--tracks-header-bg": "#191622",
    "--tracks-header-color": "#E1E1E6",

    "--success-color": "#67e480",
    "--info-color": "#78D1E1",
    "--warning-color": "#F0AD4E",
    "--danger-color": "#E96379",

    "--toasts-bg": "#191622",

    "--progress-bg": "#191622",

    "--sidebar-bg": "#201B2D",
    "--sidebar-item-active-bg": "#191622",
    "--sidebar-item-input-bg": "white",

    "--search-bg": "#191622",
    "--slider-bg": "#191622",

    "--scrollbar-track": "#988bc7",
    "--scrollbar-thumb": "rgba(255, 255, 255, 0.2)",

    "--queue-bg": "#191622",
    "--queue-header-bg": "#201B2D",

    "--checkbox-bg": "#555555",


    
    "--main-color": "#FF79C6"
  }
}
